excelschema/__init__.py
excelschema/constraint.py
excelschema/core.py
excelschema/exception.py
excelschema/util.py
excelschema-0.1.2.4.dist-info/LICENSE
excelschema-0.1.2.4.dist-info/WHEEL
excelschema-0.1.2.4.dist-info/METADATA
excelschema-0.1.2.4.dist-info/RECORD
