Metadata-Version: 2.1
Name: excelschema
Version: 0.1.2.4
Summary: Excel records' parser and schema viewing and validating tools.
Home-page: https://github.com/patarapolw/excelschema
License: UNKOWN
Keywords: excel
Author: patarapolw
Author-email: patarapolw@gmail.com
Classifier: Programming Language :: Python :: 2
Classifier: Programming Language :: Python :: 2.7
Classifier: Programming Language :: Python :: 3
Classifier: Programming Language :: Python :: 3.4
Classifier: Programming Language :: Python :: 3.5
Classifier: Programming Language :: Python :: 3.6
Classifier: Programming Language :: Python :: 3.7
Requires-Dist: python-dateutil (>=2.7,<3.0)
